prefab_cloud_django/__init__.py
prefab_cloud_django/templatetags/__init__.py
prefab_cloud_django/templatetags/prefab_tags.py
prefab_cloud_django-0.2.0.dist-info/WHEEL
prefab_cloud_django-0.2.0.dist-info/METADATA
prefab_cloud_django-0.2.0.dist-info/RECORD
