Metadata-Version: 2.1
Name: prefab-cloud-django
Version: 0.2.0
Summary: Custom template tags for using prefab-cloud-python in Django applications
Author: Michael Berkowitz
Author-email: michael.berkowitz@gmail.com
Requires-Python: >=3.10,<4.0
Classifier: Programming Language :: Python :: 3
Classifier: Programming Language :: Python :: 3.10
Classifier: Programming Language :: Python :: 3.11
Requires-Dist: Django (>=4.2,<5.0)
Requires-Dist: prefab-cloud-python (>=0.3.3)
